foot/.DS_Store
foot/__init__.py
foot/sillywalks.py
foot-0.1.0.dist-info/METADATA
foot-0.1.0.dist-info/RECORD
foot-0.1.0.dist-info/WHEEL
foot-0.1.0.dist-info/entry_points.txt
foot-0.1.0.dist-info/top_level.txt
