Metadata-Version: 2.1
Name: foot
Version: 0.1.0
Summary: Fetches a list of URLs and silly walks through each site to gather information.
Home-page: https://github.com/cakinney/foot
Author: Caleb Kinney
Author-email: cakinney@gmail.com
License: MIT license
Keywords: crawler,scraping
Platform: UNKNOWN
Classifier: Development Status :: 5 - Production/Stable
Classifier: Intended Audience :: Developers
Classifier: License :: OSI Approved :: MIT License
Classifier: Operating System :: Unix
Classifier: Operating System :: POSIX
Classifier: Operating System :: Microsoft :: Windows
Classifier: Programming Language :: Python :: 3.7
Classifier: Programming Language :: Python :: Implementation :: CPython
Classifier: Programming Language :: Python :: Implementation :: PyPy
Classifier: Topic :: Utilities
Requires-Dist: beautifulsoup4 (==4.6.3)
Requires-Dist: aiohttp (==3.4.4)
